prpip/__init__.py
prpip/_version.py
prpip/blink_detection.py
prpip/load_data.py
prpip/process.py
prpip/reconstruction.py
prpip/validation.py
prpip-1.3.2.dist-info/LICENSE
prpip-1.3.2.dist-info/METADATA
prpip-1.3.2.dist-info/WHEEL
prpip-1.3.2.dist-info/top_level.txt
prpip-1.3.2.dist-info/RECORD
