Metadata-Version: 2.1
Name: prpip
Version: 1.3.2
Summary: A package for reconstructing pupil size and handling eye-tracker blinks.
Home-page: https://github.com/AhsanKhodami/prpip
Author: Mohammad Ahsan Khodami
Requires-Python: >=3.7
License-File: LICENSE
Requires-Dist: numpy
Requires-Dist: pandas
